colors.py
bobothy_colors-1.0.3.dist-info/METADATA
bobothy_colors-1.0.3.dist-info/WHEEL
bobothy_colors-1.0.3.dist-info/top_level.txt
bobothy_colors-1.0.3.dist-info/RECORD
