Metadata-Version: 2.1
Name: bobothy-colors
Version: 1.0.3
Summary: library of rgb colors
Home-page: https://github.com/Bob-the-Bobothy/colors
Author: Bob-the-Bobothy
Requires-Python: >=2.0, >=3.0
